logger4py/__init__.py
logger4py-0.3.0.dist-info/METADATA
logger4py-0.3.0.dist-info/WHEEL
logger4py-0.3.0.dist-info/top_level.txt
logger4py-0.3.0.dist-info/RECORD
