Metadata-Version: 2.1
Name: logger4py
Version: 0.3.0
Summary: Logging Python Package
Home-page: https://gitlab.com/Mahmoudaouinti/logger4py.git
Author: IoT Team
Author-email: aouintimahmod@gmail.com
License: UNKNOWN
Keywords: sample,setuptools,development
Platform: UNKNOWN
Classifier: Development Status :: 3 - Alpha
Classifier: Intended Audience :: Developers
Classifier: Topic :: Software Development :: Build Tools
Classifier: License :: OSI Approved :: MIT License
Classifier: Programming Language :: Python :: 3
Classifier: Programming Language :: Python :: 3.6
Classifier: Programming Language :: Python :: 3.7
Classifier: Programming Language :: Python :: 3.8
Classifier: Programming Language :: Python :: 3.9
Requires-Dist: watchdog
